duckdb_extension/__init__.py
duckdb_extension/duckdb_extension.py
duckdb_extension/example_usage.py
duckdb_extension-0.1.dist-info/LICENSE
duckdb_extension-0.1.dist-info/METADATA
duckdb_extension-0.1.dist-info/WHEEL
duckdb_extension-0.1.dist-info/top_level.txt
duckdb_extension-0.1.dist-info/RECORD
