Metadata-Version: 2.1
Name: duckdb-extension
Version: 0.1
Summary: A custom PySpark extension for writing data to DuckDB
Home-page: https://github.com/yourusername/duckdb_extension
Author: Channabasav Angadi
Author-email: channuangadi077@gmail.com
License: UNKNOWN
Platform: UNKNOWN
Classifier: Programming Language :: Python :: 3
Classifier: License :: OSI Approved :: MIT License
Classifier: Operating System :: OS Independent
Requires-Python: >=3.6
License-File: LICENSE
Requires-Dist: duckdb (>=0.3.0)
Requires-Dist: pyspark (>=3.0.0)
